nautobot_circuit_maintenance/__init__.py
nautobot_circuit_maintenance/admin.py
nautobot_circuit_maintenance/api/__init__.py
nautobot_circuit_maintenance/api/serializers.py
nautobot_circuit_maintenance/api/urls.py
nautobot_circuit_maintenance/api/views.py
nautobot_circuit_maintenance/app-config-schema.json
nautobot_circuit_maintenance/choices.py
nautobot_circuit_maintenance/custom_validators.py
nautobot_circuit_maintenance/enum.py
nautobot_circuit_maintenance/filters.py
nautobot_circuit_maintenance/fixtures/handle_notifications_job.yaml
nautobot_circuit_maintenance/fixtures/source_gmail_api.yaml
nautobot_circuit_maintenance/fixtures/source_imap.yaml
nautobot_circuit_maintenance/forms.py
nautobot_circuit_maintenance/handle_notifications/__init__.py
nautobot_circuit_maintenance/handle_notifications/handler.py
nautobot_circuit_maintenance/handle_notifications/sources.py
nautobot_circuit_maintenance/jobs/__init__.py
nautobot_circuit_maintenance/jobs/location_search.py
nautobot_circuit_maintenance/metrics_app.py
nautobot_circuit_maintenance/migrations/0001_initial.py
nautobot_circuit_maintenance/migrations/0002_notification_secrets_out_of_db.py
nautobot_circuit_maintenance/migrations/0003_improve_rawnotification.py
nautobot_circuit_maintenance/migrations/0004_raw_md5.py
nautobot_circuit_maintenance/migrations/0005_notificationsource__token.py
nautobot_circuit_maintenance/migrations/0006_fake_migration_to_update_custom_fields.py
nautobot_circuit_maintenance/migrations/0007_notificationsource_attach_all_providers.py
nautobot_circuit_maintenance/migrations/0008_raw_binary.py
nautobot_circuit_maintenance/migrations/0009_auto_20210916_1519.py
nautobot_circuit_maintenance/migrations/0010_rawnotification_stamp.py
nautobot_circuit_maintenance/migrations/0011_mysql.py
nautobot_circuit_maintenance/migrations/0012_auto_20230810_1245.py
nautobot_circuit_maintenance/migrations/0013_rename_site_search_job.py
nautobot_circuit_maintenance/migrations/__init__.py
nautobot_circuit_maintenance-2.3.1.dist-info/LICENSE
nautobot_circuit_maintenance-2.3.1.dist-info/METADATA
nautobot_circuit_maintenance-2.3.1.dist-info/WHEEL
nautobot_circuit_maintenance-2.3.1.dist-info/RECORD
