Metadata-Version: 2.3
Name: nautobot-circuit-maintenance
Version: 2.3.1
Summary: Nautobot app to automatically handle Circuit Maintenances Notifications
License: Apache-2.0
Keywords: nautobot,nautobot-app,nautobot-plugin
Author: Network to Code, LLC
Author-email: opensource@networktocode.com
Requires-Python: >=3.8,<3.13
Classifier: Development Status :: 5 - Production/Stable
Classifier: Intended Audience :: Developers
Classifier: License :: OSI Approved :: Apache Software License
Classifier: Programming Language :: Python :: 3
Classifier: Programming Language :: Python :: 3.8
Classifier: Programming Language :: Python :: 3.9
Classifier: Programming Language :: Python :: 3.10
Classifier: Programming Language :: Python :: 3.11
Classifier: Programming Language :: Python :: 3.12
Provides-Extra: all
Provides-Extra: capacity-metrics
Provides-Extra: ews
Requires-Dist: circuit-maintenance-parser (>=2.0.0,<3.0.0)
Requires-Dist: django-cryptography (>=1.1,<2.0)
Requires-Dist: exchangelib (>=5.1.0) ; extra == "ews" or extra == "all"
Requires-Dist: google-api-python-client (>=2.9.0,<3.0.0)
Requires-Dist: google-auth-httplib2 (>=0.1.0,<0.2.0)
Requires-Dist: google-auth-oauthlib (>=0.5.0,<0.6.0)
Requires-Dist: markdown (!=3.3.5)
Requires-Dist: nautobot (>=2.0.0,<3.0.0)
Requires-Dist: nautobot-capacity-metrics (>=3.0.0) ; extra == "capacity-metrics" or extra == "all"
Requires-Dist: pydantic (>=1.10.4,<3)
Project-URL: Documentation, https://docs.nautobot.com/projects/circuit-maintenance/en/latest/
Project-URL: Homepage, https://github.com/nautobot/nautobot-app-circuit-maintenance
Project-URL: Repository, https://github.com/nautobot/nautobot-app-circuit-maintenance
